atro_args/__init__.py
atro_args/arg.py
atro_args/arg_casting.py
atro_args/arg_signature.py
atro_args/arg_source.py
atro_args/class_populating.py
atro_args/decorators.py
atro_args/helpers.py
atro_args/input_args.py
atro_args/source_loading.py
atro_args-0.7.15.dist-info/LICENSE
atro_args-0.7.15.dist-info/METADATA
atro_args-0.7.15.dist-info/WHEEL
atro_args-0.7.15.dist-info/RECORD
