Metadata-Version: 2.1
Name: atro-args
Version: 0.7.15
Summary: 
Author: atropos
Author-email: sv7n@pm.me
Requires-Python: >=3.11,<4.0
Classifier: Programming Language :: Python :: 3
Classifier: Programming Language :: Python :: 3.11
Classifier: Programming Language :: Python :: 3.12
Requires-Dist: atro-utils (>=0.0.8,<0.0.9)
Requires-Dist: pydantic (>=2.3.0,<3.0.0)
Requires-Dist: python-dotenv (>=1.0.0,<2.0.0)
Requires-Dist: pyyaml (>=6.0.1,<7.0.0)
Requires-Dist: types-pyyaml (>=6.0.12.11,<7.0.0.0)
